fn_ont_expunge/__init__.py
fn_ont_expunge/exceptions.py
fn_ont_expunge/ont_expunge.py
fn_ont_expunge-0.2.dist-info/LICENSE.txt
fn_ont_expunge-0.2.dist-info/METADATA
fn_ont_expunge-0.2.dist-info/WHEEL
fn_ont_expunge-0.2.dist-info/top_level.txt
fn_ont_expunge-0.2.dist-info/RECORD
